kabbes_nanoid/Client.py
kabbes_nanoid/Nanoid.py
kabbes_nanoid/__init__.py
kabbes_nanoid/__main__.py
kabbes_nanoid-0.7.0.dist-info/LICENSE
kabbes_nanoid-0.7.0.dist-info/METADATA
kabbes_nanoid-0.7.0.dist-info/WHEEL
kabbes_nanoid-0.7.0.dist-info/top_level.txt
kabbes_nanoid-0.7.0.dist-info/RECORD
