Metadata-Version: 2.1
Name: kabbes-nanoid
Version: 0.7.0
Summary: Python library for generating NanoIDs
Home-page: https://pypi.org/project/kabbes-nanoid/
Author: James Kabbes
Author-email: james.kabbes@gmail.com
Project-URL: GitHub, https://github.com/jameskabbes/nanoid
Project-URL: Documentation, https://jameskabbes.github.io/nanoid
Classifier: Programming Language :: Python :: 3
Classifier: License :: OSI Approved :: MIT License
Classifier: Operating System :: OS Independent
Requires-Python: >=3.7
License-File: LICENSE
Requires-Dist: kabbes-parent-class
Requires-Dist: kabbes-dir-ops
Requires-Dist: kabbes-client
